tutti_language_detector/__init__.py
tutti_language_detector/wrapper.py
tutti_language_detector/models/vw-0.0.1.model
tutti_language_detector/models/vw-0.0.2.model
tutti_language_detector-2.0.2.dist-info/LICENSE
tutti_language_detector-2.0.2.dist-info/METADATA
tutti_language_detector-2.0.2.dist-info/WHEEL
tutti_language_detector-2.0.2.dist-info/top_level.txt
tutti_language_detector-2.0.2.dist-info/zip-safe
tutti_language_detector-2.0.2.dist-info/RECORD
