Metadata-Version: 2.1
Name: tutti-language-detector
Version: 2.0.2
Summary: A tutti specific language detector.
Home-page: UNKNOWN
Author: Oscar Saleta
Author-email: oscar@tutti.ch
License: Proprietary
Keywords: language,detector
Platform: UNKNOWN
Classifier: Programming Language :: Python :: 3
Classifier: Operating System :: OS Independent
Requires-Python: >=3.5.2
Requires-Dist: numpy (>=1.17.3)
Requires-Dist: pandas (>=0.25.3)
Requires-Dist: scikit-learn (>=0.20.3)
